tornado_alchemy_rest/__init__.py
tornado_alchemy_rest/encoders.py
tornado_alchemy_rest-1.0.18.dist-info/METADATA
tornado_alchemy_rest-1.0.18.dist-info/RECORD
tornado_alchemy_rest-1.0.18.dist-info/WHEEL
tornado_alchemy_rest-1.0.18.dist-info/top_level.txt
