Metadata-Version: 2.1
Name: tornado-alchemy-rest
Version: 1.0.18
Summary: Tornado REST API
Home-page: https://github.com/EzyInsights/tornado-alchemy-rest
Author: EzyInsights team
Author-email: andrii.kostenko@kampiki.com
License: Apache
Keywords: tornado sqlalchemy alchemy rest api postgresql
Platform: UNKNOWN
Classifier: Development Status :: 4 - Beta
Classifier: Intended Audience :: Developers
Classifier: License :: OSI Approved :: Apache Software License
Classifier: Programming Language :: Python :: 3
Classifier: Programming Language :: Python :: 3.3
Classifier: Programming Language :: Python :: 3.4
Classifier: Programming Language :: Python :: 3.5
Provides-Extra: dev
Provides-Extra: test
Requires-Dist: tornado
Requires-Dist: sqlalchemy
Provides-Extra: dev
Requires-Dist: check-manifest; extra == 'dev'
Provides-Extra: test
Requires-Dist: coverage; extra == 'test'
